{
  "parent": "minecraft:recipes/root",
  "criteria": {
    "has_the_recipe": {
      "trigger": "minecraft:recipe_unlocked",
      "conditions": {
        "recipe": "gm4_block_compressors:compressor"
      }
    },
    "has_materials": {
      "trigger": "minecraft:inventory_changed",
      "conditions": {
        "items": [
          {
            "items": [
              "minecraft:purpur_block",
              "minecraft:purpur_pillar",
              "minecraft:piston",
              "minecraft:obsidian"
            ]
          }
        ]
      }
    }
  },
  "requirements": [
    [
      "has_the_recipe",
      "has_materials"
    ]
  ],
  "rewards": {
    "recipes": [
      "gm4_block_compressors:compressor"
    ]
  }
}
