{
  "display": {
    "icon": {
      "item": "minecraft:cauldron",
      "nbt": "{CustomModelData:3420002}"
    },
    "title": {
      "text": "Check your guidebook!",
      "color": "#4AA0C7",
      "italic": true
    },
    "description": "Zauber Cauldrons",
    "frame": "goal",
    "show_toast": true,
    "announce_to_chat": false,
    "hidden": true
  },
  "parent": "gm4_guidebook:zauber_cauldrons/page_1",
  "criteria": {
    "requirement": {
      "trigger": "minecraft:tick",
      "conditions": {
        "player": [
          {
            "condition": "minecraft:inverted",
            "term": {
              "condition": "minecraft:entity_properties",
              "entity": "this",
              "predicate": {
                "type_specific": {
                  "type": "player",
                  "gamemode": "spectator"
                }
              }
            }
          },
          {
            "condition": "minecraft:value_check",
            "value": {
              "type": "minecraft:score",
              "target": {
                "type": "minecraft:fixed",
                "name": "gm4_guidebook"
              },
              "score": "load.status"
            },
            "range": 1
          },
          {
            "condition": "minecraft:value_check",
            "value": {
              "type": "minecraft:score",
              "target": {
                "type": "minecraft:fixed",
                "name": "gm4_zauber_cauldrons"
              },
              "score": "load.status"
            },
            "range": 1
          },
          {
            "condition": "minecraft:entity_properties",
            "entity": "this",
            "predicate": {
              "type_specific": {
                "type": "player",
                "advancements": {
                  "gm4:zauber_cauldrons_create": true
                }
              }
            }
          }
        ]
      }
    },
    "unlocked_future_page": {
      "trigger": "minecraft:tick",
      "conditions": {
        "player": [
          {
            "condition": "minecraft:inverted",
            "term": {
              "condition": "minecraft:entity_properties",
              "entity": "this",
              "predicate": {
                "type_specific": {
                  "type": "player",
                  "gamemode": "spectator"
                }
              }
            }
          },
          {
            "condition": "minecraft:value_check",
            "value": {
              "type": "minecraft:score",
              "target": {
                "type": "minecraft:fixed",
                "name": "gm4_guidebook"
              },
              "score": "load.status"
            },
            "range": 1
          },
          {
            "condition": "minecraft:value_check",
            "value": {
              "type": "minecraft:score",
              "target": {
                "type": "minecraft:fixed",
                "name": "gm4_zauber_cauldrons"
              },
              "score": "load.status"
            },
            "range": 1
          },
          {
            "condition": "minecraft:entity_properties",
            "entity": "this",
            "predicate": {
              "type_specific": {
                "type": "player",
                "advancements": {
                  "gm4_guidebook:zauber_cauldrons/page_11": true
                }
              }
            }
          }
        ]
      }
    }
  },
  "requirements": [
    [
      "requirement",
      "unlocked_future_page"
    ]
  ],
  "rewards": {
    "function": "gm4_zauber_cauldrons:guidebook/unlock_page"
  }
}
