{
  "pools": [
    {
      "rolls": 1,
      "entries": [
        {
          "type": "minecraft:item",
          "name": "minecraft:player_head",
          "functions": [
            {
              "function": "minecraft:set_nbt",
              "tag": "{CustomModelData:3420009,gm4_scuba_gear:{item:\"helmet\"},AttributeModifiers:[{AttributeName:\"generic.armor\",Name:\"generic.armor\",Amount:2,Operation:0,UUID:[I;0,190244,0,554768],Slot:\"head\"},{AttributeName:\"generic.attack_speed\",Name:\"generic.attack_speed\",Amount:-.5,Operation:0,UUID:[I;0,193195,0,454101],Slot:\"head\"}],SkullOwner:{Name:\"[Drop to Fix Item] gm4_scuba_gear:scuba_helmet\",Properties:{textures:[{Value:\"$scuba_helmet\"}]}}}"
            },
            {
              "function": "minecraft:set_name",
              "name": {
                "translate": "item.gm4.scuba_helmet",
                "fallback": "SCUBA Helmet",
                "italic": false,
                "color": "white"
              }
            }
          ]
        }
      ]
    }
  ]
}
