{
    "display": {
      "icon": {
        "item": "minecraft:clock",
        "nbt": "{CustomModelData:3420001,Enchantments:[{}]}"
      },
      "title": {
        "translate": "%1$s%3427655$s",
        "with": [
          "Give me More!",
          {
            "translate": "advancement.gm4.combat_evolved.challenger.title"
          }
        ]
      },
      "description": {
        "translate": "%1$s%3427655$s",
        "with": [
          "When tough is not good enough",
          {
            "translate": "advancement.gm4.combat_evolved.challenger.description"
          }
        ]
      },
      "frame": "challenge"
    },
    "parent": "gm4:combat_evolved_survive",
    "criteria": {
      "challenger": {
        "trigger": "minecraft:impossible"
      }
    }
  }
  