{
  "type": "generic",
  "pools": [
    {
      "rolls": 1,
      "entries": [
        {
          "type": "item",
          "weight": 1,
          "name": "minecraft:potion",
          "functions": [
            {
              "function": "set_count",
              "count": 1
            },
            {
              "function": "set_nbt",
              "tag": "{custom_potion:\"booze\",CustomPotionEffects:[{Id:2b,Amplifier:0b,Duration:1200},{Id:5b,Amplifier:0b,Duration:1200},{Id:9b,Amplifier:1b,Duration:400},{Id:19b,Amplifier:0b,Duration:400},{Id:22b,Amplifier:1b,Duration:1200}],CustomPotionColor:11236936}"
            },
            {
              "function": "set_name",
              "name": [
                {
                  "text": "Booze"
                }
              ]
            }
          ]
        }
      ]
    }
  ]
}
