{
    "parent": "minecraft:block/iron_block",
    "overrides": [
        {
            "predicate": {
                "custom_model_data": 1
            },
            "model": "gm4:gui/advancements/icon/guidebook/tinkering_compressors"
        },
        {
            "predicate": {
                "custom_model_data": 2
            },
            "model": "gm4:block/smelteries/smeltery_unlit"
        },
        {
            "predicate": {
                "custom_model_data": 3
            },
            "model": "gm4:block/smelteries/smeltery_lit"
        },
        {
            "predicate": {
                "custom_model_data": 4
            },
            "model": "minecraft:item/iron_block"
        },
        {
            "predicate": {
                "custom_model_data": 3420001
            },
            "model": "gm4:gui/advancements/icon/guidebook/tinkering_compressors"
        },
        {
            "predicate": {
                "custom_model_data": 3420002
            },
            "model": "gm4:block/smelteries/smeltery_unlit"
        },
        {
            "predicate": {
                "custom_model_data": 3420003
            },
            "model": "gm4:block/smelteries/smeltery_lit"
        },
        {
            "predicate": {
                "custom_model_data": 3420004
            },
            "model": "minecraft:item/iron_block"
        }
    ]
}
