{
  "id": "resurrecting_zombies",
  "name": "Resurrecting Zombies",
  "module_type": "expansion",
  "load_check": "mysterious_midnights",
  "base_module": "mysterious_midnights",
  "icon": {
    "item": "minecraft:rotten_flesh",
    "nbt": "{CustomModelData:3420002}"
  },
  "criteria": {
    "page_0/requirement": {
      "trigger": "minecraft:tick",
      "conditions": {
        "player": [
          {
            "condition": "minecraft:entity_properties",
            "entity": "this",
            "predicate": {
              "type_specific": {
                "type": "player",
                "looking_at": {
                  "type": "minecraft:zombie",
                  "nbt": "{DeathLootTable:\"minecraft:empty\",Attributes:[{Name:\"minecraft:generic.attack_damage\",Base:10.0d}]}"
                }
              }
            }
          }
        ]
      }
    }
  },
  "sections": [
    {
      "name": "page_0",
      "enable": [],
      "requirements": [
        [
          "page_0/requirement"
        ]
      ],
      "pages": [
        [
          {
            "insert": "title"
          },
          {
            "translate": "text.gm4.guidebook.resurrecting_zombies.1",
            "fallback": "During a Resurrecting Zombies event, rotten flesh on the floor will resurrect into unarmed zombies, with a powerful attack."
          }
        ]
      ]
    }
  ]
}
