{
    "display": {
        "icon": {
            "id": "minecraft:splash_potion",
            "components": {
                "minecraft:custom_model_data": "gui/advancement/display_frames",
                "minecraft:potion_contents": "minecraft:invisibility"
            }
        },
        "title": {
            "translate": "advancement.gm4.display_frames.title",
            "fallback": "Where Did It Go?"
        },
        "description": {
            "translate": "advancement.gm4.display_frames.description",
            "fallback": "Make an item frame invisible with a splash potion of invisibility",
            "color": "gray"
        }
    },
    "parent": "gm4:root",
    "criteria": {
        "impossible": {
            "trigger": "minecraft:impossible"
        }
    }
}
