{
  "type": "minecraft:chest",
  "pools": [
    {
      "rolls": {
        "min": 3,
        "max": 10,
        "type": "minecraft:uniform"
      },
      "entries": [
        {
          "type": "minecraft:item",
          "weight": 10,
          "functions": [
            {
              "function": "minecraft:set_stew_effect",
              "effects": [
                {
                  "type": "minecraft:night_vision",
                  "duration": {
                    "min": 7,
                    "max": 10
                  }
                },
                {
                  "type": "minecraft:poison",
                  "duration": {
                    "min": 3,
                    "max": 4
                  }
                },
                {
                  "type": "minecraft:saturation",
                  "duration": {
                    "min": 7,
                    "max": 10
                  }
                },
                {
                  "type": "minecraft:jump_boost",
                  "duration": {
                    "min": 7,
                    "max": 10
                  }
                },
                {
                  "type": "minecraft:weakness",
                  "duration": {
                    "min": 6,
                    "max": 8
                  }
                },
                {
                  "type": "minecraft:blindness",
                  "duration": {
                    "min": 5,
                    "max": 7
                  }
                },
                {
                  "type": "minecraft:fire_resistance",
                  "duration": {
                    "min": 2,
                    "max": 4
                  }
                },
                {
                  "type": "minecraft:regeneration",
                  "duration": {
                    "min": 6,
                    "max": 8
                  }
                }
              ]
            }
          ],
          "name": "minecraft:suspicious_stew"
        }
      ]
    }
  ]
}
