{
  "type": "minecraft:generic",
  "pools": [
    {
      "rolls": 1,
      "entries": [
        {
          "type": "minecraft:item",
          "name": "minecraft:stone"
        }
      ],
      "functions": [
        {
          "function": "minecraft:set_name",
          "entity": "this",
          "name": [
            {
              "translate": "%1$s%3427655$s",
              "with": [
                [
                  {
                    "text": "Satiated ",
                    "italic": false,
                    "color": "yellow"
                  },
                  {
                    "nbt": "tag.gm4_combat_expanded.name",
                    "storage": "gm4_combat_expanded:temp",
                    "interpret": true,
                    "color": "yellow"
                  }
                ],
                {
                  "translate": "item.gm4.combat_expanded.name.satiated",
                  "with": [
                    {
                      "nbt": "tag.gm4_combat_expanded.name",
                      "storage": "gm4_combat_expanded:temp",
                      "interpret": true,
                      "color": "yellow"
                    }
                  ]
                }
              ]
            }
          ]
        }
      ]
    }
  ]
}
