{
  "display": {
    "icon": {
      "item": "enchanted_book",
      "nbt": "{CustomModelData:3420001}"
    },
    "frame": "goal",
    "title": {
      "translate": "advancement.gm4.enchantment_extractors.mending.title",
      "fallback": "Magical Thief"
    },
    "description": {
      "translate": "advancement.gm4.enchantment_extractors.mending.description",
      "fallback": "Successfully extract the mending enchantment from a tool with an Enchantment Extractor",
      "color": "gray"
    }
  },
  "parent": "gm4:enchantment_extractors",
  "criteria": {
    "extract_mending": {
      "trigger": "minecraft:impossible"
    }
  }
}
