{
  "pools": [
    {
      "rolls": 1,
      "entries": [
        {
          "type": "minecraft:item",
          "name": "minecraft:trident",
          "functions": [
            {
              "function": "minecraft:set_nbt",
              "tag": "{HideFlags:3,Enchantments:[{}]}"
            },
            {
              "function": "minecraft:set_name",
              "name": {
                "translate": "item.gm4.spell_trident",
                "fallback": "Spell Trident",
                "color": "yellow",
                "italic": false
              }
            },
            {
              "function": "minecraft:set_attributes",
              "modifiers": [
                {
                  "attribute": "minecraft:generic.attack_damage",
                  "name": "gm4_hy_spell_trident_dam",
                  "amount": 0,
                  "operation": "addition",
                  "slot": "mainhand"
                }
              ]
            },
            {
              "function": "minecraft:set_damage",
              "damage": 0.99
            }
          ]
        }
      ]
    }
  ]
}
